ptv_timetable/__init__.py
ptv_timetable/asyncapi.py
ptv_timetable/types.py
tramtracker/__init__.py
tramtracker/asyncapi.py
tramtracker/types.py
ptv_timetable-0.4.1.dist-info/LICENCE.md
ptv_timetable-0.4.1.dist-info/METADATA
ptv_timetable-0.4.1.dist-info/WHEEL
ptv_timetable-0.4.1.dist-info/top_level.txt
ptv_timetable-0.4.1.dist-info/RECORD
