Metadata-Version: 2.2
Name: ptv-timetable
Version: 0.4.1
Summary: API wrappers for interacting with real-time public transport data in Victoria, Australia
Author-email: pizza1016 <10370007-pizza1016@users.noreply.gitlab.com>
Maintainer-email: pizza1016 <10370007-pizza1016@users.noreply.gitlab.com>
License: # Copyright and licensing
Project-URL: Documentation, https://gitlab.com/pizza1016/ptv-timetable/-/blob/trunk/README.md
Project-URL: Repository, https://gitlab.com/pizza1016/ptv-timetable
Project-URL: Issues, https://gitlab.com/pizza1016/ptv-timetable/-/issues
Keywords: public transport,transportation,melbourne,victoria,australia,ptv,public transport victoria,metro trains,yarra trams,vline,library,api wrapper
Classifier: Development Status :: 3 - Alpha
Classifier: Intended Audience :: Developers
Classifier: License :: OSI Approved :: Apache Software License
Classifier: Operating System :: OS Independent
Classifier: Programming Language :: Python :: 3
Classifier: Programming Language :: Python :: 3.12
Classifier: Programming Language :: Python :: 3.13
Classifier: Programming Language :: Python :: 3.14
Classifier: Topic :: Other/Nonlisted Topic
Classifier: Topic :: Software Development :: Libraries :: Python Modules
Classifier: Topic :: Utilities
Classifier: Typing :: Typed
Requires-Python: >=3.12
License-File: LICENCE.md
Requires-Dist: aiohttp>=3.11.11
Requires-Dist: aiolimiter>=1.2.1
Requires-Dist: ratelimit>=2.2.1
Requires-Dist: requests>=2.32.3
Requires-Dist: tzdata>=2024.1; platform_system == "Windows"
